{"noiseKey":{"private":{"type":"Buffer","data":"uKPyDhYHhRGW+xSfJ/IZbYSAMyrRCtA3cj97xTIcj1M="},"public":{"type":"Buffer","data":"dzUA9vQdZfs1YOPDgf4qM5L99m+4ZM++sa06shVdQWM="}},"pairingEphemeralKeyPair":{"private":{"type":"Buffer","data":"mHDOy0zDXRb23HiHDGEIcXtNN+CqQ4/iQj78BD7hkUc="},"public":{"type":"Buffer","data":"ODIFq6ireZNzgso75q0cc2o0OM9NhSJmZUzMCEzJDA4="}},"signedIdentityKey":{"private":{"type":"Buffer","data":"CEsvUkVNXFWRotnSQ6NqIHygOzM+xpDQvVl4BQDekXM="},"public":{"type":"Buffer","data":"wivmLWjfw5kYW7+XJKhmUggjmR7SYYBNTplKf0Q/xSk="}},"signedPreKey":{"keyPair":{"private":{"type":"Buffer","data":"qOz5rqk39oFBIbIe2dBCeKqLuuzZ2en9HOwP+HLUWlk="},"public":{"type":"Buffer","data":"FIblZqGVeJdLaXAmXIQuFWG4xF3yBRL/aS65ns8vEDU="}},"signature":{"type":"Buffer","data":"LJyD50lK1g8yiEfJCaGNnjaluIfwXsiJAToM817zfaZv1UxmPn++F4tS2MImUm6Po7GKxZGpJE0hNNrSbTNjBg=="},"keyId":1},"registrationId":130,"advSecretKey":"edRUq/B+sE6oXBaqvtQ2L4NkrOPg+al1/FFi3luSXno=","processedHistoryMessages":[{"key":{"remoteJid":"5219611137503@s.whatsapp.net","fromMe":false,"id":"3A107EA5A519CE4E6528","participant":"","addressingMode":"pn"},"messageTimestamp":1769050607},{"key":{"remoteJid":"5219611137503@s.whatsapp.net","fromMe":false,"id":"3AD79175896E1CBB1C82","participant":"","addressingMode":"pn"},"messageTimestamp":1769050609},{"key":{"remoteJid":"5219611137503@s.whatsapp.net","fromMe":false,"id":"3A499C4E28B57DC69175","participant":"","addressingMode":"pn"},"messageTimestamp":1769050609},{"key":{"remoteJid":"5219611137503@s.whatsapp.net","fromMe":false,"id":"3A6226287FDEB17349FA","participant":"","addressingMode":"pn"},"messageTimestamp":1769050609},{"key":{"remoteJid":"5219611137503@s.whatsapp.net","fromMe":false,"id":"3AC9508A7AD64B511742","participant":"","addressingMode":"pn"},"messageTimestamp":1769050616},{"key":{"remoteJid":"5219611137503@s.whatsapp.net","fromMe":false,"id":"3AB7A29C8CB1909714CD","participant":"","addressingMode":"pn"},"messageTimestamp":1769050720},{"key":{"remoteJid":"5219611137503@s.whatsapp.net","fromMe":false,"id":"3A8EA7EA2928BB12F2DD","participant":"","addressingMode":"pn"},"messageTimestamp":1769050723},{"key":{"remoteJid":"5219611137503@s.whatsapp.net","fromMe":false,"id":"3AE2254EBC7CDB03D45E","participant":"","addressingMode":"pn"},"messageTimestamp":1769050727},{"key":{"remoteJid":"5219611137503@s.whatsapp.net","fromMe":false,"id":"3AB4B95D968279982C4F","participant":"","addressingMode":"pn"},"messageTimestamp":1769050751},{"key":{"remoteJid":"5219611137503@s.whatsapp.net","fromMe":false,"id":"3A8AD85BDE5AA9F76DB6","participant":"","addressingMode":"pn"},"messageTimestamp":1769050751},{"key":{"remoteJid":"5219611137503@s.whatsapp.net","fromMe":false,"id":"3AAF79445DF78C7C77B8","participant":"","addressingMode":"pn"},"messageTimestamp":1769050764},{"key":{"remoteJid":"5219611137503@s.whatsapp.net","fromMe":false,"id":"3ADF13B07EEA18FD33C6","participant":"","addressingMode":"pn"},"messageTimestamp":1769050949},{"key":{"remoteJid":"5219611137503@s.whatsapp.net","fromMe":false,"id":"3A355F72C43044A616AB","participant":"","addressingMode":"pn"},"messageTimestamp":1769050949},{"key":{"remoteJid":"5219611137503@s.whatsapp.net","fromMe":false,"id":"3A02112BD6954C86F128","participant":"","addressingMode":"pn"},"messageTimestamp":1769050953},{"key":{"remoteJid":"5219611137503@s.whatsapp.net","fromMe":false,"id":"3A54ED3D587E04652DC9","participant":"","addressingMode":"pn"},"messageTimestamp":1769050957},{"key":{"remoteJid":"5219611137503@s.whatsapp.net","fromMe":false,"id":"3AB6587D798D56680D90","participant":"","addressingMode":"pn"},"messageTimestamp":1769050964},{"key":{"remoteJid":"5219611137503@s.whatsapp.net","fromMe":false,"id":"3AE8366D4625D034C825","participant":"","addressingMode":"pn"},"messageTimestamp":1769050964},{"key":{"remoteJid":"5219611137503@s.whatsapp.net","fromMe":false,"id":"3AA3B3B87876973E6615","participant":"","addressingMode":"pn"},"messageTimestamp":1769050968},{"key":{"remoteJid":"5219611137503@s.whatsapp.net","fromMe":false,"id":"3A1F37D5BCB2DBFF71FC","participant":"","addressingMode":"pn"},"messageTimestamp":1769050971},{"key":{"remoteJid":"5219611137503@s.whatsapp.net","fromMe":false,"id":"3A4E9D1B046FA7DCE98D","participant":"","addressingMode":"pn"},"messageTimestamp":1769050999},{"key":{"remoteJid":"5219611137503@s.whatsapp.net","fromMe":false,"id":"3ADC9F23FCFC13FEC234","participant":"","addressingMode":"pn"},"messageTimestamp":1769050999},{"key":{"remoteJid":"5219611137503@s.whatsapp.net","fromMe":false,"id":"3A76B1667683831B62FA","participant":"","addressingMode":"pn"},"messageTimestamp":1769051051},{"key":{"remoteJid":"5219611137503@s.whatsapp.net","fromMe":false,"id":"3A55A2886BC3EC3B2106","participant":"","addressingMode":"pn"},"messageTimestamp":1769051052},{"key":{"remoteJid":"5219611137503@s.whatsapp.net","fromMe":false,"id":"3AD8B28C5182B3192D06","participant":"","addressingMode":"pn"},"messageTimestamp":1769051231},{"key":{"remoteJid":"5219611137503@s.whatsapp.net","fromMe":false,"id":"3A4C6CC399BEE8A4C59E","participant":"","addressingMode":"pn"},"messageTimestamp":1769051231},{"key":{"remoteJid":"5219611137503@s.whatsapp.net","fromMe":false,"id":"3A89911CE8B8C9DE6760","participant":"","addressingMode":"pn"},"messageTimestamp":1769051231},{"key":{"remoteJid":"5219611137503@s.whatsapp.net","fromMe":false,"id":"3A1B263DE7153B87A683","participant":"","addressingMode":"pn"},"messageTimestamp":1769051298},{"key":{"remoteJid":"5219611137503@s.whatsapp.net","fromMe":false,"id":"3AA3E6D1CE03E1A70CF9","participant":"","addressingMode":"pn"},"messageTimestamp":1769051298},{"key":{"remoteJid":"5219611137503@s.whatsapp.net","fromMe":false,"id":"3AF295F68D3EB5F941B0","participant":"","addressingMode":"pn"},"messageTimestamp":1769051544},{"key":{"remoteJid":"5219611137503@s.whatsapp.net","fromMe":false,"id":"3A82A02C34C9B2CDE087","participant":"","addressingMode":"pn"},"messageTimestamp":1769051544},{"key":{"remoteJid":"5219611137503@s.whatsapp.net","fromMe":false,"id":"3A58840476CB293E9F5B","participant":"","addressingMode":"pn"},"messageTimestamp":1769051551},{"key":{"remoteJid":"5219611137503@s.whatsapp.net","fromMe":false,"id":"3A80606ACF41DD9DC4D1","participant":"","addressingMode":"pn"},"messageTimestamp":1769051554},{"key":{"remoteJid":"5219611137503@s.whatsapp.net","fromMe":false,"id":"3ABA0B0B026541E3BD90","participant":"","addressingMode":"pn"},"messageTimestamp":1769051558},{"key":{"remoteJid":"5219611137503@s.whatsapp.net","fromMe":false,"id":"3A48C7EC8F4224142CCE","participant":"","addressingMode":"pn"},"messageTimestamp":1769051565},{"key":{"remoteJid":"5219611137503@s.whatsapp.net","fromMe":false,"id":"3A120D5BFEAD5094BB83","participant":"","addressingMode":"pn"},"messageTimestamp":1769051565},{"key":{"remoteJid":"5219611137503@s.whatsapp.net","fromMe":false,"id":"3A2973760F3F4FB1195A","participant":"","addressingMode":"pn"},"messageTimestamp":1769051571},{"key":{"remoteJid":"5219611137503@s.whatsapp.net","fromMe":false,"id":"3A306BA7F22C56EE9199","participant":"","addressingMode":"pn"},"messageTimestamp":1769051571},{"key":{"remoteJid":"5219611137503@s.whatsapp.net","fromMe":false,"id":"3A5A8E7ACCC4AC439A49","participant":"","addressingMode":"pn"},"messageTimestamp":1769051574},{"key":{"remoteJid":"5219611137503@s.whatsapp.net","fromMe":false,"id":"3A46B5F9E88D11908028","participant":"","addressingMode":"pn"},"messageTimestamp":1769051579},{"key":{"remoteJid":"5219611137503@s.whatsapp.net","fromMe":false,"id":"3ABC57568B636A1179B4","participant":"","addressingMode":"pn"},"messageTimestamp":1769051581},{"key":{"remoteJid":"5219611137503@s.whatsapp.net","fromMe":false,"id":"3A84C2CCA55A841A7041","participant":"","addressingMode":"pn"},"messageTimestamp":1769051583},{"key":{"remoteJid":"5219611137503@s.whatsapp.net","fromMe":false,"id":"3AF8CA288037B9C3410B","participant":"","addressingMode":"pn"},"messageTimestamp":1769051586},{"key":{"remoteJid":"5219611137503@s.whatsapp.net","fromMe":false,"id":"3AC25C312B2187C3D575","participant":"","addressingMode":"pn"},"messageTimestamp":1769051587},{"key":{"remoteJid":"5219611137503@s.whatsapp.net","fromMe":false,"id":"3A9F2E6A71DF06A62A03","participant":"","addressingMode":"pn"},"messageTimestamp":1769051589},{"key":{"remoteJid":"5219611137503@s.whatsapp.net","fromMe":false,"id":"3AC84328F5964369BAA8","participant":"","addressingMode":"pn"},"messageTimestamp":1769051614},{"key":{"remoteJid":"5219611137503@s.whatsapp.net","fromMe":false,"id":"3A638F63DED7279AF34A","participant":"","addressingMode":"pn"},"messageTimestamp":1769051614},{"key":{"remoteJid":"5219611137503@s.whatsapp.net","fromMe":false,"id":"3AC4E8F8A768A54EDE5D","participant":"","addressingMode":"pn"},"messageTimestamp":1769051634},{"key":{"remoteJid":"5219611137503@s.whatsapp.net","fromMe":false,"id":"3A9D78975A51AD3A3301","participant":"","addressingMode":"pn"},"messageTimestamp":1769051634},{"key":{"remoteJid":"5219611137503@s.whatsapp.net","fromMe":false,"id":"3A9D448AD88032DE159B","participant":"","addressingMode":"pn"},"messageTimestamp":1769051634},{"key":{"remoteJid":"5219611137503@s.whatsapp.net","fromMe":false,"id":"3AD1DC40D4F6D6ACB2BE","participant":"","addressingMode":"pn"},"messageTimestamp":1769051638},{"key":{"remoteJid":"5219611137503@s.whatsapp.net","fromMe":false,"id":"3A79840E5CDEB268E88D","participant":"","addressingMode":"pn"},"messageTimestamp":1769051640},{"key":{"remoteJid":"5219611137503@s.whatsapp.net","fromMe":false,"id":"3AF104B30B47EDB057C5","participant":"","addressingMode":"pn"},"messageTimestamp":1769051641},{"key":{"remoteJid":"5219611137503@s.whatsapp.net","fromMe":false,"id":"3AB01AE657ACBD573253","participant":"","addressingMode":"pn"},"messageTimestamp":1769051645},{"key":{"remoteJid":"5219611137503@s.whatsapp.net","fromMe":false,"id":"3AE0371A15E9287E237C","participant":"","addressingMode":"pn"},"messageTimestamp":1769051645},{"key":{"remoteJid":"5219611137503@s.whatsapp.net","fromMe":false,"id":"3A61AFC705FD267BFC3E","participant":"","addressingMode":"pn"},"messageTimestamp":1769051646},{"key":{"remoteJid":"5219611137503@s.whatsapp.net","fromMe":false,"id":"3A8CDD9AFB70D79E59B5","participant":"","addressingMode":"pn"},"messageTimestamp":1769051650},{"key":{"remoteJid":"5219611137503@s.whatsapp.net","fromMe":false,"id":"3A8F80FE6A5DB8493136","participant":"","addressingMode":"pn"},"messageTimestamp":1769051650},{"key":{"remoteJid":"5219611137503@s.whatsapp.net","fromMe":false,"id":"3A04AF449B596EC5320F","participant":"","addressingMode":"pn"},"messageTimestamp":1769051652},{"key":{"remoteJid":"5219611137503@s.whatsapp.net","fromMe":false,"id":"3ADAF1805B28335E3459","participant":"","addressingMode":"pn"},"messageTimestamp":1769051660},{"key":{"remoteJid":"5219611137503@s.whatsapp.net","fromMe":false,"id":"3A17FA8D9EDF524F78CF","participant":"","addressingMode":"pn"},"messageTimestamp":1769051660},{"key":{"remoteJid":"5219611137503@s.whatsapp.net","fromMe":false,"id":"3A1830B9B48FF258C1C5","participant":"","addressingMode":"pn"},"messageTimestamp":1769051672},{"key":{"remoteJid":"5219611137503@s.whatsapp.net","fromMe":false,"id":"3A544B84F1E933000CAF","participant":"","addressingMode":"pn"},"messageTimestamp":1769051702},{"key":{"remoteJid":"5219611137503@s.whatsapp.net","fromMe":false,"id":"3A9A8B613BE10A9D9770","participant":"","addressingMode":"pn"},"messageTimestamp":1769051702},{"key":{"remoteJid":"5219611137503@s.whatsapp.net","fromMe":false,"id":"3A8067C1D62C94DA5097","participant":"","addressingMode":"pn"},"messageTimestamp":1769051702},{"key":{"remoteJid":"5219611137503@s.whatsapp.net","fromMe":false,"id":"3AEAE393C2B1FB30FF1B","participant":"","addressingMode":"pn"},"messageTimestamp":1769051708}],"nextPreKeyId":815,"firstUnuploadedPreKeyId":815,"accountSyncCounter":1,"accountSettings":{"unarchiveChats":false},"registered":false,"account":{"details":"CJnzyYsDEOijxssGGI0BIAAoAA==","accountSignatureKey":"TS3/7C9AN/Q6++nEpIHcaU1215/2AcMfMltoCoxcqCc=","accountSignature":"FNW6zOJNg/aZmof3UBJ+GM4RPFjATM+B4+qRsoO095CqWcwjEHmEHHVIQT1PPsHgF4/ZfQUrc82qe09cw3O9BA==","deviceSignature":"Ltlv5IvAkm9ersRrTNzdID9aX8A2ldkpjA1Vkh7vMeF3v1Iy2XW/xf/r+42D67huXjQwgbfjhYBm9iJ2G70eBg=="},"me":{"id":"5219611137503:87@s.whatsapp.net","lid":"194910078669031:87@lid","name":"Diego"},"signalIdentities":[{"identifier":{"name":"194910078669031:87@lid","deviceId":0},"identifierKey":{"type":"Buffer","data":"BU0t/+wvQDf0OvvpxKSB3GlNdtef9gHDHzJbaAqMXKgn"}}],"platform":"iphone","routingInfo":{"type":"Buffer","data":"CAgIDQgF"},"lastAccountSyncTimestamp":1769050606,"lastPropHash":"2V77qU","myAppStateKeyId":"AAAAAJPs"}